avido/__init__.py
avido/_base_client.py
avido/_client.py
avido/_compat.py
avido/_constants.py
avido/_exceptions.py
avido/_files.py
avido/_models.py
avido/_qs.py
avido/_resource.py
avido/_response.py
avido/_streaming.py
avido/_types.py
avido/_version.py
avido/pagination.py
avido/py.typed
avido/_utils/__init__.py
avido/_utils/_compat.py
avido/_utils/_datetime_parse.py
avido/_utils/_json.py
avido/_utils/_logs.py
avido/_utils/_proxy.py
avido/_utils/_reflection.py
avido/_utils/_resources_proxy.py
avido/_utils/_streams.py
avido/_utils/_sync.py
avido/_utils/_transform.py
avido/_utils/_typing.py
avido/_utils/_utils.py
avido/lib/.keep
avido/resources/__init__.py
avido/resources/annotations.py
avido/resources/applications.py
avido/resources/documents.py
avido/resources/ingest.py
avido/resources/runs.py
avido/resources/style_guides.py
avido/resources/tasks.py
avido/resources/tests.py
avido/resources/topics.py
avido/resources/traces.py
avido/resources/validate_webhook.py
avido/types/__init__.py
avido/types/annotation_create_params.py
avido/types/annotation_list_params.py
avido/types/annotation_list_response.py
avido/types/annotation_response.py
avido/types/application_create_params.py
avido/types/application_list_params.py
avido/types/application_list_response.py
avido/types/application_response.py
avido/types/document_create_params.py
avido/types/document_list_chunks_params.py
avido/types/document_list_chunks_response.py
avido/types/document_list_params.py
avido/types/document_list_response.py
avido/types/document_response.py
avido/types/ingest_create_params.py
avido/types/ingest_create_response.py
avido/types/run_list_params.py
avido/types/run_list_response.py
avido/types/run_retrieve_response.py
avido/types/style_guide_create_params.py
avido/types/style_guide_list_params.py
avido/types/style_guide_list_response.py
avido/types/style_guide_response.py
avido/types/task_create_params.py
avido/types/task_list_params.py
avido/types/task_list_response.py
avido-1.17.0.dist-info/METADATA
avido-1.17.0.dist-info/WHEEL
avido-1.17.0.dist-info/licenses/LICENSE
avido-1.17.0.dist-info/RECORD
